dycifer/__init__.py
dycifer/analog.py
dycifer/dycifer.py
dycifer/mixed_signals.py
dycifer/read.py
dycifer/utils.py
dycifer-0.1.1.dist-info/entry_points.txt
dycifer-0.1.1.dist-info/LICENSE
dycifer-0.1.1.dist-info/WHEEL
dycifer-0.1.1.dist-info/METADATA
dycifer-0.1.1.dist-info/RECORD
